{"buildTime":"2020-06-12T20:43:44.603Z","sources":[{"id":"ComicExtra","name":"ComicExtra","author":"Conrad Weiser","desc":"Extension that pulls western comics from ComicExtra","website":"http://github.com/conradweiser","version":"0.6.5","icon":"logo.png"},{"id":"EHentai","name":"(BETA) E-Hentai","author":"Conrad Weiser","desc":"Beta extension that pulls manga from E-Hentai. Some functionality may be missing still.","website":"https://github.com/ConradWeiser","version":"0.1.5","icon":"logo.png"},{"id":"IsekaiScan","name":"IsekaiScan (Aggregator)","author":"Abdullah Mohamed","desc":"Madara source which pulls manga from the IsekaiScan website","website":null,"version":"0.0.3","icon":"icon.png"},{"id":"MangaDex","name":"MangaDex","author":"Faizan Durrani","desc":"Extension that pulls manga from MangaDex, includes Advanced Search and Updated manga fetching","website":"https://github.com/FaizanDurrani","version":"1.0.15","icon":"icon.png"},{"id":"MangaFox","name":"MangaFox","author":"Sirus","desc":"Extension that pulls manga from MangaFox, includes Advanced Search and Updated manga fetching","website":"https://github.com/Sirush","version":"1.1.1","icon":"icon.png"},{"id":"MangaLife","name":"Manga4Life","author":"Daniel Kovalevich","desc":"Extension that pulls manga from MangaLife, includes Advanced Search and Updated manga fetching","website":"https://github.com/DanielKovalevich","version":"0.5.6","icon":"icon.png"},{"id":"MangaPark","name":"MangaPark","author":"Daniel Kovalevich","desc":"Extension that pulls manga from MangaPark, includes Advanced Search and Updated manga fetching","website":"https://github.com/DanielKovalevich","version":"1.0.6","icon":"icon.png"},{"id":"Manganelo","name":"Manganelo","author":"Daniel Kovalevich","desc":"Extension that pulls manga from Manganelo, includes Advanced Search and Updated manga fetching","website":"https://github.com/DanielKovalevich","version":"1.1.1","icon":"icon.png"},{"id":"Mangasee","name":"Mangasee","author":"Daniel Kovalevich","desc":"Extension that pulls manga from Mangasee, includes Advanced Search and Updated manga fetching","website":"https://github.com/DanielKovalevich","version":"1.0.6","icon":"icon.png"},{"id":"ManhwaEighteen","name":"Manhwa18 (18+)","author":"Conrad Weiser","desc":"Extension that pulls manga from Manhwa18","website":"http://github.com/conradweiser","version":"0.6.0","icon":"logo.png"},{"id":"NHentai","name":"nHentai","author":"Conrad Weiser","desc":"Extension that pulls manga from nHentai","website":"http://github.com/conradweiser","version":"0.7.3","icon":"logo.png"},{"id":"NHentaiRedirected","name":"nHentai (Country-Proof)","author":"Conrad Weiser","desc":"nHentai source which is guaranteed to work in countries the website is normally blocked. May be a tad slower than the other source","website":"http:github.com/conradweiser","version":"0.7.3","icon":"logo.png"},{"id":"WebToons","name":"WebToons (BETA)","author":"Conrad Weiser","desc":"Extension that pulls comics from WebToons","website":"http://github.com/conradweiser","version":"0.1.2","icon":"logo.jpg"}]}